calcite/__init__.py
calcite/data_widget.py
calcite/graph_widget.py
calcite/main.py
calcite/main_window.py
calcite/pandas_model.py
calcite/plot.py
calcite/properties_widget.py
calcite/results_widget.py
calcite/dialogs/__init__.py
calcite/dialogs/advanced_filter_dialog.py
calcite/dialogs/anova_dialog.py
calcite/dialogs/calculate_dialog.py
calcite/dialogs/contingency_dialog.py
calcite/dialogs/correlation_dialog.py
calcite/dialogs/filter_dialog.py
calcite/dialogs/kruskal_dialog.py
calcite/dialogs/license_dialog.py
calcite/dialogs/mannwhitney_dialog.py
calcite/dialogs/paired_ttest_dialog.py
calcite/dialogs/pivot_dialog.py
calcite/dialogs/regression_dialog.py
calcite/dialogs/restructure_dialog.py
calcite/dialogs/ttest_dialog.py
calcite/dialogs/wilcoxon_dialog.py
calcite/handlers/__init__.py
calcite/handlers/action_handler.py
calcite/handlers/graph_manager.py
calcite/handlers/statistical_handler.py
calcite/tabs/__init__.py
calcite/tabs/axes_tab.py
calcite/tabs/data_tab.py
calcite/tabs/data_tab_paired.py
calcite/tabs/data_tab_tidy.py
calcite/tabs/format_tab.py
calcite/tabs/text_tab.py
calcite-0.4.7.dist-info/METADATA
calcite-0.4.7.dist-info/WHEEL
calcite-0.4.7.dist-info/entry_points.txt
calcite-0.4.7.dist-info/top_level.txt
calcite-0.4.7.dist-info/RECORD
