Metadata-Version: 2.4
Name: calcite
Version: 0.4.7
Summary: A desktop application for data analysis and publication-quality graphing.
Home-page: https://github.com/ryuabiru/calcite
Author: R. Abiru
Author-email: 
Classifier: Programming Language :: Python :: 3
Classifier: License :: OSI Approved :: MIT License
Classifier: Operating System :: OS Independent
Requires-Python: >=3.10
Requires-Dist: PySide6
Requires-Dist: pandas
Requires-Dist: numpy
Requires-Dist: seaborn
Requires-Dist: scipy
Requires-Dist: statsmodels
Requires-Dist: scikit-posthocs
Requires-Dist: statannotations
Requires-Dist: matplotlib
Dynamic: author
Dynamic: classifier
Dynamic: description
Dynamic: description-content-type
Dynamic: home-page
Dynamic: requires-dist
Dynamic: requires-python
Dynamic: summary
